README.rst
setup.cfg
setup.py
pyskel.egg-info/PKG-INFO
pyskel.egg-info/SOURCES.txt
pyskel.egg-info/dependency_links.txt
pyskel.egg-info/not-zip-safe
pyskel.egg-info/requires.txt
pyskel.egg-info/top_level.txt
riomucho/__init__.py
riomucho/scripts/__init__.py
riomucho/scripts/cli.py
riomucho/scripts/multiple_inputs.py