Metadata-Version: 1.0
Name: pyskel
Version: 0.0.1dev
Summary: Parallel processing wrapper for rasterio
Home-page: https://github.com/mapbox/pyskel
Author: Damon Burgett
Author-email: damon@mapbox.com
License: MIT
Platform: UNKNOWN
